pcf8574_io/PCF85.py
pcf8574_io/__init__.py
pcf8574_io-0.1.1.dist-info/LICENSE.txt
pcf8574_io-0.1.1.dist-info/METADATA
pcf8574_io-0.1.1.dist-info/WHEEL
pcf8574_io-0.1.1.dist-info/top_level.txt
pcf8574_io-0.1.1.dist-info/RECORD
