Metadata-Version: 2.1
Name: pcf8574-io
Version: 0.1.1
Summary: PCF8574 driver to set pin mode, read and write digital signal 3.3v 
Home-page: https://github.com/ahmed9378/pcf8574_io
Author: Ahmed Omar
Author-email: ahmed.bm78@gmail.com
License: MIT
Keywords: PCF8574
Platform: UNKNOWN
Classifier: Development Status :: 5 - Production/Stable
Classifier: Intended Audience :: Education
Classifier: Operating System :: Other OS
Classifier: Topic :: System :: Hardware :: Hardware Drivers
Classifier: License :: OSI Approved :: MIT License
Classifier: Programming Language :: Python :: 3
License-File: LICENSE.txt
Requires-Dist: smbus2
